odoo/addons/account_invoice_report_grouped_by_picking_hide_pickings/README.rst
odoo/addons/account_invoice_report_grouped_by_picking_hide_pickings/__init__.py
odoo/addons/account_invoice_report_grouped_by_picking_hide_pickings/__manifest__.py
odoo/addons/account_invoice_report_grouped_by_picking_hide_pickings/i18n/es.po
odoo/addons/account_invoice_report_grouped_by_picking_hide_pickings/models/__init__.py
odoo/addons/account_invoice_report_grouped_by_picking_hide_pickings/models/account_move.py
odoo/addons/account_invoice_report_grouped_by_picking_hide_pickings/models/res_company.py
odoo/addons/account_invoice_report_grouped_by_picking_hide_pickings/models/res_config_settings.py
odoo/addons/account_invoice_report_grouped_by_picking_hide_pickings/models/stock_picking.py
odoo/addons/account_invoice_report_grouped_by_picking_hide_pickings/readme/CONFIGURE.md
odoo/addons/account_invoice_report_grouped_by_picking_hide_pickings/readme/CONTRIBUTORS.md
odoo/addons/account_invoice_report_grouped_by_picking_hide_pickings/readme/DESCRIPTION.md
odoo/addons/account_invoice_report_grouped_by_picking_hide_pickings/readme/USAGE.md
odoo/addons/account_invoice_report_grouped_by_picking_hide_pickings/static/description/icon.png
odoo/addons/account_invoice_report_grouped_by_picking_hide_pickings/static/description/index.html
odoo/addons/account_invoice_report_grouped_by_picking_hide_pickings/tests/__init__.py
odoo/addons/account_invoice_report_grouped_by_picking_hide_pickings/tests/test_account_invoice_report_grouped_by_picking_hide_pickings.py
odoo/addons/account_invoice_report_grouped_by_picking_hide_pickings/views/res_config_settings_views.xml
odoo/addons/account_invoice_report_grouped_by_picking_hide_pickings/views/stock_picking_views.xml
odoo/addons/account_invoice_report_grouped_by_picking_hide_pickings/wizards/__init__.py
odoo/addons/account_invoice_report_grouped_by_picking_hide_pickings/wizards/stock_picking_return.py
odoo_addon_account_invoice_report_grouped_by_picking_hide_pickings-16.0.1.1.0.dist-info/METADATA
odoo_addon_account_invoice_report_grouped_by_picking_hide_pickings-16.0.1.1.0.dist-info/WHEEL
odoo_addon_account_invoice_report_grouped_by_picking_hide_pickings-16.0.1.1.0.dist-info/top_level.txt
odoo_addon_account_invoice_report_grouped_by_picking_hide_pickings-16.0.1.1.0.dist-info/RECORD
