Metadata-Version: 2.1
Name: odoo-addon-account_invoice_report_grouped_by_picking_hide_pickings
Version: 16.0.1.1.0
Requires-Python: >=3.10
Requires-Dist: odoo-addon-account_invoice_report_grouped_by_picking>=16.0dev,<16.1dev
Requires-Dist: odoo>=16.0a,<16.1dev
Summary: Hide pickings on the account invoice report grouped by pickings
Home-page: https://github.com/sygel-technology/sy-account-invoice-reporting
License: AGPL-3
Author: Sygel, Odoo Community Association (OCA)
Author-email: support@odoo-community.org
Classifier: Programming Language :: Python
Classifier: Framework :: Odoo
Classifier: Framework :: Odoo :: 16.0
Classifier: License :: OSI Approved :: GNU Affero General Public License v3
